sukeerthiq3/__init__.py
sukeerthiq3/operations.py
sukeerthiq3-0.0.7.dist-info/METADATA
sukeerthiq3-0.0.7.dist-info/WHEEL
sukeerthiq3-0.0.7.dist-info/top_level.txt
sukeerthiq3-0.0.7.dist-info/RECORD
